LICENSE
README.rst
manual_requirements.txt
requirements.txt
setup.py
streamlit_state/__init__.py
streamlit_state.egg-info/PKG-INFO
streamlit_state.egg-info/SOURCES.txt
streamlit_state.egg-info/dependency_links.txt
streamlit_state.egg-info/requires.txt
streamlit_state.egg-info/top_level.txt